helloworld.py
helloworld_avborodin-0.0.2.dist-info/METADATA
helloworld_avborodin-0.0.2.dist-info/WHEEL
helloworld_avborodin-0.0.2.dist-info/top_level.txt
helloworld_avborodin-0.0.2.dist-info/RECORD
