Metadata-Version: 2.1
Name: helloworld-avborodin
Version: 0.0.2
Summary: Say hello
Home-page: UNKNOWN
Author: Andrey Borodin
Author-email: boroddon@gmail.com
License: UNKNOWN
Platform: UNKNOWN
